pyhgtmap/NASASRTMUtil.py
pyhgtmap/__init__.py
pyhgtmap/cli.py
pyhgtmap/configuration.py
pyhgtmap/latlon.py
pyhgtmap/logger.py
pyhgtmap/main.py
pyhgtmap/varint.py
pyhgtmap/hgt/__init__.py
pyhgtmap/hgt/contour.py
pyhgtmap/hgt/file.py
pyhgtmap/hgt/processor.py
pyhgtmap/hgt/tile.py
pyhgtmap/output/__init__.py
pyhgtmap/output/factory.py
pyhgtmap/output/o5mUtil.py
pyhgtmap/output/osmUtil.py
pyhgtmap/output/pbfUtil.py
pyhgtmap/sources/__init__.py
pyhgtmap/sources/alos.py
pyhgtmap/sources/pool.py
pyhgtmap/sources/sonny.py
pyhgtmap/sources/viewfinder.py
pyhgtmap-3.8.dist-info/METADATA
pyhgtmap-3.8.dist-info/WHEEL
pyhgtmap-3.8.dist-info/entry_points.txt
pyhgtmap-3.8.dist-info/licenses/LICENSE.md
pyhgtmap-3.8.dist-info/RECORD
