Metadata-Version: 2.4
Name: pyhgtmap
Version: 3.8
Summary: Creates OpenStreetMap suitable contour lines from NASA SRTM data
Project-URL: repository, https://github.com/agrenott/pyhgtmap
Author-email: Adrian Dempwolff <phyghtmap@aldw.de>, Aurélien Grenotton <agrenott@gmail.com>
License-Expression: GPL-2.0-or-later
License-File: LICENSE.md
Keywords: OpenStreetMap,SRTM,countour,elevation,osm
Classifier: Development Status :: 5 - Production/Stable
Classifier: Environment :: Console
Classifier: License :: OSI Approved :: GNU General Public License v2 or later (GPLv2+)
Classifier: Operating System :: MacOS
Classifier: Operating System :: POSIX :: Linux
Classifier: Programming Language :: Python
Classifier: Programming Language :: Python :: 3
Classifier: Topic :: Scientific/Engineering :: GIS
Requires-Python: >=3.9
Requires-Dist: bs4>=0.0.1
Requires-Dist: colorlog>=6.7.0
Requires-Dist: configargparse>=1.7
Requires-Dist: contourpy>=1.0.7
Requires-Dist: httpx>=0.27.0
Requires-Dist: lxml>=4.9.2
Requires-Dist: matplotlib>=3.4.3
Requires-Dist: nptyping>=2.5.0
Requires-Dist: npyosmium>=3.6.1
Requires-Dist: numpy>=1.24.2
Requires-Dist: phx-class-registry<5,>=4.0.6
Requires-Dist: pybind11-rdp>=0.1.3
Requires-Dist: pydrive2>=1.20.0
Requires-Dist: scipy>=1.8.0
Requires-Dist: shapely>=2.0.1
Provides-Extra: geotiff
Requires-Dist: gdal; extra == 'geotiff'
